[
    {
        "image": "./assets/Rectangle 22.png",
        "name": "Dr. Ruhani Singh",
        "qualification": "MBBS, MD (DVL)",
        "specialty": "Specialist: Dermatologist, Skin Care, Hair",
        "location": "Tagore Town, Prayagraj",
        "experience": "16+ years of experience",
        "ratings":"****",
        "ratingCount":"4.0",
        "fee": 200
    },
    {
        "image": "./assets/Rectangle 22.png",
        "name": "Dr. Ruhani Singh",
        "qualification": "MBBS, MD (DVL)",
        "specialty": "Specialist: Dermatologist, Skin Care, Hair",
        "location": "Tagore Town, Prayagraj",
        "experience": "16+ years of experience",
        "ratings":"****",
        "ratingCount":"4.0",
        "fee": 200
    },
    {
        "image": "./assets/Rectangle 22.png",
        "name": "Dr. Ruhani Singh",
        "qualification": "MBBS, MD (DVL)",
        "specialty": "Specialist: Dermatologist, Skin Care, Hair",
        "location": "Tagore Town, Prayagraj",
        "experience": "16+ years of experience",
        "ratings":"****",
        "ratingCount":"4.0",
        "fee": 200
    },
    {
        "image": "./assets/Rectangle 22.png",
        "name": "Dr. Ruhani Singh",
        "qualification": "MBBS, MD (DVL)",
        "specialty": "Specialist: Dermatologist, Skin Care, Hair",
        "location": "Tagore Town, Prayagraj",
        "experience": "16+ years of experience",
        "ratings":"****",
        "ratingCount":"4.0",
        "fee": 200
    },
    {
        "image": "./assets/Rectangle 22.png",
        "name": "Dr. Ruhani Singh",
        "qualification": "MBBS, MD (DVL)",
        "specialty": "Specialist: Dermatologist, Skin Care, Hair",
        "location": "Tagore Town, Prayagraj",
        "experience": "16+ years of experience",
        "ratings":"****",
        "ratingCount":"4.0",
        "fee": 200
    },  
    {
        "image": "./assets/Rectangle 22.png",
        "name": "Dr. Ruhani Singh",
        "qualification": "MBBS, MD (DVL)",
        "specialty": "Specialist: Dermatologist, Skin Care, Hair",
        "location": "Tagore Town, Prayagraj",
        "experience": "16+ years of experience",
        "ratings":"****",
        "ratingCount":"4.0",
        "fee": 200
    }
]